ami_push/__init__.py
ami_push/bridge.py
ami_push/cli.py
ami_push/controller.py
ami_push/filters.py
ami_push/messages.py
ami_push/pusher.py
ami_push/utils.py
ami_push-0.1.1.dist-info/LICENSE
ami_push-0.1.1.dist-info/METADATA
ami_push-0.1.1.dist-info/WHEEL
ami_push-0.1.1.dist-info/RECORD
